{
  "type": "tfc:advanced_shapeless_crafting",
  "ingredients": [
    {
      "type": "tfc:not_rotten",
      "ingredient": {
        "tag": "tfc:food/fruits"
      }
    },
    {
      "type": "tfc:not_rotten",
      "ingredient": {
        "tag": "tfc:food/fruits"
      }
    },
    {
      "type": "tfc:not_rotten",
      "ingredient": {
        "tag": "tfc:food/fruits"
      }
    },
    {
      "type": "tfc:not_rotten",
      "ingredient": {
        "tag": "tfc:food/fruits"
      }
    },
    {
      "type": "tfc:not_rotten",
      "ingredient": {
        "tag": "tfc:food/fruits"
      }
    },
    {
      "type": "tfc:not_rotten",
      "ingredient": {
        "tag": "tfc:food/fruits"
      }
    },
    {
      "item": "minecraft:bowl"
    }
  ],
  "result": {
    "item": "farmersdelight:fruit_salad"
  }
}